hexacolors/__init__.py
hexacolors/colors/__colors__.py
hexacolors/colors/__listcolors__.py
hexacolors/colors/blue.py
hexacolors/colors/brown.py
hexacolors/colors/cyan.py
hexacolors/colors/gray.py
hexacolors/colors/green.py
hexacolors/colors/ligthcolors.py
hexacolors/colors/orange.py
hexacolors/colors/pink.py
hexacolors/colors/purple.py
hexacolors/colors/red.py
hexacolors/colors/yellow.py
hexacolors/offline/converoff.py
hexacolors/offline/str.py
hexacolors/online/api.py
hexacolors/online/autodetect.py
hexacolors/online/client/clientlogin.py
hexacolors-0.6.0.dist-info/METADATA
hexacolors-0.6.0.dist-info/WHEEL
hexacolors-0.6.0.dist-info/top_level.txt
hexacolors-0.6.0.dist-info/RECORD
