Metadata-Version: 2.1
Name: hexacolors
Version: 0.6.0
Summary: :A simple library that converts string to hexadecimal understandable by python
Author: Marciel404
License: MIT
Project-URL: Homepage, https://github.com/Marciel404/hexacolors
Keywords: Python understandable colors
Classifier: License :: OSI Approved :: MIT License
Classifier: Intended Audience :: Developers
Classifier: Natural Language :: Portuguese
Classifier: Operating System :: OS Independent
Classifier: Programming Language :: Python :: 3.10
Classifier: Programming Language :: Python :: 3.11
Classifier: Topic :: Software Development :: Libraries
Classifier: Topic :: Software Development :: Libraries :: Python Modules
Classifier: Topic :: Utilities
Classifier: Typing :: Typed
Requires-Python: >=3.10
Requires-Dist: aiohttp
